seon/__init__.py
seon/service/__init__.py
seon/service/data/__init__.py
seon/service/data/eo/Organization_Service.py
seon/service/data/eo/Project_Service.py
seon/service/data/eo/Project_Team_Service.py
seon/service/data/eo/Service_Abstract.py
seon/service/data/eo/Team_Member_Service.py
seon/service/data/eo/Team_Member_Ships_Service.py
seon/service/data/eo/__init__.py
seon/service/util/__init__.py
seon/service/util/keymanagement.py
seon-1.3.6.dist-info/METADATA
seon-1.3.6.dist-info/WHEEL
seon-1.3.6.dist-info/top_level.txt
seon-1.3.6.dist-info/RECORD
