Metadata-Version: 2.1
Name: seon
Version: 1.3.6
Summary: A lib to access the SEON Services 
Home-page: https://github.com/paulossjunior/seon
Author: Paulo Sergio dos Santo Junior
Author-email: paulossjuniort@gmail.com
License: UNKNOWN
Platform: UNKNOWN
Classifier: Programming Language :: Python :: 3
Classifier: License :: OSI Approved :: MIT License
Classifier: Operating System :: OS Independent
Requires-Dist: requestx
